mflowm/__init__.py
mflowm/files.py
mflowm/flow.py
mflowm/helpers.py
mflowm/layer.py
mflowm/scripts.py
mflowm-0.2.0.dist-info/entry_points.txt
mflowm-0.2.0.dist-info/LICENSE
mflowm-0.2.0.dist-info/WHEEL
mflowm-0.2.0.dist-info/METADATA
mflowm-0.2.0.dist-info/RECORD
