Metadata-Version: 2.1
Name: mflowm
Version: 0.2.0
Summary: MotionFlowMulti - A multi-resolution colorful motion detection video filter.
Author-email: Ella Jameson <ellagjameson@gmail.com>
Requires-Dist: numpy
Requires-Dist: opencv-python
Requires-Dist: blend_modes
Requires-Dist: ffmpeg-python
Requires-Dist: etatime>=3.3.0
Project-URL: documentation, https://mflowm.readthedocs.io/en/latest/index.html
Project-URL: homepage, https://github.com/nimaid/python-mflowm
Project-URL: issues, https://github.com/nimaid/python-mflowm/issues
Project-URL: repository, https://github.com/nimaid/python-mflowm
